convigure/__init__.py
convigure/convigure.py
convigure-0.2.0.dist-info/LICENSE
convigure-0.2.0.dist-info/METADATA
convigure-0.2.0.dist-info/WHEEL
convigure-0.2.0.dist-info/top_level.txt
convigure-0.2.0.dist-info/RECORD
