Metadata-Version: 2.1
Name: convigure
Version: 0.2.0
Summary: Easy configuration for Python with dot notation.
Home-page: https://github.com/rendicahya/convigure
Author: Randy Cahya Wihandika
Author-email: rendicahya@gmail.com
Classifier: Programming Language :: Python :: 3
Classifier: License :: OSI Approved :: GNU General Public License v3 (GPLv3)
Classifier: Operating System :: OS Independent
Requires-Python: >=3.6
License-File: LICENSE
Requires-Dist: toml
